{
  "model_id": "crofai/greg-1-super",
  "organisation_id": "crofai",
  "name": "Greg 1 Super",
  "status": "Retired",
  "previous_model_id": null,
  "description": "Greg 1 Super is CrofAI's premium Greg 1 variant, tuned for higher-capability responses while keeping the same long text context window.",
  "announced_date": "2026-01-27T18:50:50",
  "release_date": "2026-01-27T18:50:50",
  "deprecation_date": null,
  "retirement_date": "2026-06-17T00:00:00",
  "license": null,
  "input_types": "text",
  "output_types": "text",
  "api_model_id": "crofai/greg-1-super",
  "links": [
    {
      "platform": "website",
      "url": "https://crof.ai/pricing"
    }
  ],
  "details": [
    {
      "name": "input_context_length",
      "value": 229376
    },
    {
      "name": "output_context_length",
      "value": 229376
    },
    {
      "name": "availability",
      "value": "Removed from CrofAI's /v1/models feed by 2026-06-17. Two-week notice sent to active users."
    }
  ],
  "benchmarks": []
}
