{
  "model_id": "mistral/codestral-2024-05-29",
  "organisation_id": "mistral",
  "name": "Codestral (2024-05-29)",
  "status": "Retired",
  "previous_model_id": null,
  "description": "Codestral (2024-05-29) is a coding model from Mistral for code generation, edits, and software tasks. It accepts text inputs and produces text outputs.",
  "announced_date": "2024-05-29T00:00:00",
  "release_date": "2024-05-29T00:00:00",
  "deprecation_date": "2024-12-02T00:00:00",
  "retirement_date": "2025-06-16T00:00:00",
  "license": "Mistral AI Non Production License",
  "input_types": "text",
  "output_types": "text",
  "api_model_id": "mistral/codestral-2024-05-29",
  "links": [
    {
      "platform": "api_reference",
      "url": "https://docs.mistral.ai/api/"
    },
    {
      "platform": "playground",
      "url": "https://chat.mistral.ai/"
    },
    {
      "platform": "announcement",
      "url": "https://mistral.ai/news/codestral/"
    },
    {
      "platform": "weights",
      "url": "https://huggingface.co/mistralai/Codestral-22B-v0.1"
    }
  ],
  "details": [
    {
      "name": "input_context_length",
      "value": 32768
    },
    {
      "name": "output_context_length",
      "value": 32768
    },
    {
      "name": "parameter_count",
      "value": 22200000000
    }
  ],
  "benchmarks": [
    {
      "benchmark_id": "cruxeval-o",
      "score": 0.513,
      "is_self_reported": true,
      "other_info": "inferred modality/version alias from codestral-22b",
      "source_link": "https://mistral.ai/news/codestral/",
      "rank": 5
    },
    {
      "benchmark_id": "humaneval",
      "score": 81.1,
      "is_self_reported": true,
      "other_info": "inferred modality/version alias from codestral-22b",
      "source_link": "https://mistral.ai/news/codestral/",
      "rank": 59
    },
    {
      "benchmark_id": "humaneval-average",
      "score": 0.615,
      "is_self_reported": true,
      "other_info": "inferred modality/version alias from codestral-22b",
      "source_link": "https://mistral.ai/news/codestral/",
      "rank": 2
    },
    {
      "benchmark_id": "humanevalfim-average",
      "score": 0.916,
      "is_self_reported": true,
      "other_info": "inferred modality/version alias from codestral-22b",
      "source_link": "https://mistral.ai/news/codestral/",
      "rank": 2
    },
    {
      "benchmark_id": "mbpp",
      "score": 0.782,
      "is_self_reported": true,
      "other_info": "inferred modality/version alias from codestral-22b",
      "source_link": "https://mistral.ai/news/codestral/",
      "rank": 19
    },
    {
      "benchmark_id": "repobench",
      "score": 0.34,
      "is_self_reported": true,
      "other_info": "inferred modality/version alias from codestral-22b",
      "source_link": "https://mistral.ai/news/codestral/",
      "rank": 2
    },
    {
      "benchmark_id": "spider",
      "score": 0.635,
      "is_self_reported": true,
      "other_info": "inferred modality/version alias from codestral-22b",
      "source_link": "https://mistral.ai/news/codestral/",
      "rank": 2
    }
  ]
}
